simpletexting/__init__.py
simpletexting-0.0.1.dist-info/METADATA
simpletexting-0.0.1.dist-info/WHEEL
simpletexting-0.0.1.dist-info/top_level.txt
simpletexting-0.0.1.dist-info/RECORD
