Metadata-Version: 2.1
Name: simpletexting
Version: 0.0.1
Summary: A Python Module for Simple Texting's API
Home-page: https://github.com/tboswick/Simple-Texting
Author: Tom Boswick
Author-email: taboswick@example.com
License: UNKNOWN
Keywords: Simple Texting
Platform: UNKNOWN
Classifier: Programming Language :: Python :: 3
Classifier: License :: OSI Approved :: MIT License
Classifier: Operating System :: OS Independent
Requires-Python: >=3.6
Requires-Dist: xmltodict
Requires-Dist: requests
